README.md
setup.py
entangld/__init__.py
entangld/entangld.py
entangld.egg-info/PKG-INFO
entangld.egg-info/SOURCES.txt
entangld.egg-info/dependency_links.txt
entangld.egg-info/top_level.txt