Metadata-Version: 2.1
Name: entangld
Version: 1.0.1
Summary: Synchronized key-value stores with RPCs and pub/sub events. (Port of node.js version)
Home-page: https://github.com/DaxBot/python-entangld
Author: Jonathan D B Van Schenck
Author-email: jvschenck@novadynamics.com
License: UNKNOWN
Platform: UNKNOWN
Classifier: Programming Language :: Python :: 3
Classifier: License :: OSI Approved :: MIT License
Requires-Python: >=3.6
